pyslinger/__init__.py
pyslinger/main.py
pyslinger-0.2.1.dist-info/METADATA
pyslinger-0.2.1.dist-info/WHEEL
pyslinger-0.2.1.dist-info/top_level.txt
pyslinger-0.2.1.dist-info/RECORD
