Metadata-Version: 2.1
Name: pyslinger
Version: 0.2.1
Summary: Python package to ping slack
Author: satya.penamakuri
Author-email: satya.penamakuri@gmail.com
